minecraft_launcher_cmd/__init__.py
minecraft_launcher_cmd/minecraft_launcher_cmd.py
minecraft_launcher_cmd-1.1.dist-info/LICENSE
minecraft_launcher_cmd-1.1.dist-info/METADATA
minecraft_launcher_cmd-1.1.dist-info/WHEEL
minecraft_launcher_cmd-1.1.dist-info/entry_points.txt
minecraft_launcher_cmd-1.1.dist-info/top_level.txt
minecraft_launcher_cmd-1.1.dist-info/RECORD
